aucc/__init__.py
aucc/main.py
aucc/core/__init__.py
aucc/core/colors.py
aucc/core/handler.py
aucc/core/__pycache__/__init__.cpython-37.pyc
aucc/core/__pycache__/colors.cpython-37.pyc
aucc/core/__pycache__/handler.cpython-37.pyc
aucc/db/__init__.py
aucc/res/icons/tux.png
aucc/ui/__init__.py
avell_unofficial_control_center-1.0.1.dist-info/LICENSE
avell_unofficial_control_center-1.0.1.dist-info/METADATA
avell_unofficial_control_center-1.0.1.dist-info/WHEEL
avell_unofficial_control_center-1.0.1.dist-info/entry_points.txt
avell_unofficial_control_center-1.0.1.dist-info/top_level.txt
avell_unofficial_control_center-1.0.1.dist-info/RECORD
