Metadata-Version: 2.1
Name: avell-unofficial-control-center
Version: 1.0.1
Summary: A Project to provide a driver and interface to control keyboard rgb led of ITE 8291 like Avell laptops
Home-page: https://github.com/rodgomesc/avell-unofficial-control-center
Author: Rodrigo Gomes da Cunha
Author-email: rodgomesc@gmail.com
License: UNKNOWN
Project-URL: Bug Reports, https://github.com/rodgomesc/avell-unofficial-control-center/issues
Project-URL: Funding, https://www.buymeacoffee.com/KCZRP52U7
Project-URL: Source, https://github.com/rodgomesc/avell-unofficial-control-center
Platform: UNKNOWN
Requires-Dist: pyusb
Requires-Dist: elevate
